meds_etl/__init__.py
meds_etl/_version.py
meds_etl/omop.py
meds_etl/unsorted.py
meds_etl/utils.py
meds_etl/mimic/__init__.py
meds_etl/mimic/concept_map/LICENSE
meds_etl/mimic/concept_map/README
meds_etl/mimic/concept_map/d_labitems_to_loinc.csv
meds_etl/mimic/concept_map/inputevents_to_rxnorm.csv
meds_etl/mimic/concept_map/lab_itemid_to_loinc.csv
meds_etl/mimic/concept_map/meas_chartevents_main.csv
meds_etl/mimic/concept_map/meas_chartevents_value.csv
meds_etl/mimic/concept_map/numerics-summary.csv
meds_etl/mimic/concept_map/outputevents_to_loinc.csv
meds_etl/mimic/concept_map/proc_datetimeevents.csv
meds_etl/mimic/concept_map/proc_itemid.csv
meds_etl/mimic/concept_map/waveforms-summary.csv
meds_etl-0.3.11.dist-info/licenses/LICENSE
meds_etl-0.3.11.dist-info/METADATA
meds_etl-0.3.11.dist-info/WHEEL
meds_etl-0.3.11.dist-info/entry_points.txt
meds_etl-0.3.11.dist-info/top_level.txt
meds_etl-0.3.11.dist-info/RECORD
