Metadata-Version: 2.4
Name: meds_etl
Version: 0.3.11
Summary: A data standard for working with event stream data
License: Apache-2.0
License-File: LICENSE
Requires-Dist: pyarrow>=8
Requires-Dist: polars>=1.22
Requires-Dist: jsonschema>=4.0.0
Requires-Dist: meds==0.3.3
Requires-Dist: typing_extensions>=4.0
Requires-Dist: tqdm>=4.6.0
Provides-Extra: cpp
Requires-Dist: meds_etl_cpp==0.3.4; extra == "cpp"
Dynamic: license-file
